pcappy_port
httpcap
