Metadata-Version: 1.1
Name: httpcap
Version: 0.7.9
Summary: Capture and parse http traffics with python
Home-page: https://github.com/caoqianli/httpcap
Author: xiaxiaocao
Author-email: dongliu@live.cn
License: Simplified BSD License
Platform: UNKNOWN
Classifier: Programming Language :: Python
Classifier: Intended Audience :: Developers
Classifier: Operating System :: OS Independent
Classifier: Programming Language :: Python :: 2
Classifier: Programming Language :: Python :: 3
